{
  "domain": "www.cnnindonesia.com",
  "crawling_time": "2024-01-08 13:07:26.487546",
  "crawling_time_epoch": 1704694046,
  "url": "https://www.cnnindonesia.com/indeks/2/129",
  "title": "VIDEO: Turki Tangkap 34 Orang Dicurigai Mata-mata Israel",
  "categories": "Internasional",
  "article": {
    "content_url": "https://www.cnnindonesia.com/internasional/20240103125952-139-1044762/video-turki-tangkap-34-orang-dicurigai-mata-mata-israel",
    "posted": "Rabu, 03 Jan 2024 13:19 WIB",
    "media_url": null,
    "tags": [
      "mata-mata israel",
      "turki tangkap mata-mata israel",
      "israel",
      "turki",
      "CNN INDONESIA TV"
    ],
    "article": "Polisi Turki menahan 34 orang yang dicurigai menjadi mata-mata untuk dinas intelijen Mossad Israel pada Selasa (2 1). Badan Intelijen Nasional (MIT) menargetkan orang asing yang tinggal di Turki. Sebanyak 46 orang yang memiliki hubungan intelijen Israel telah diidentifikasi. Namun, beberapa dari mereka telah pergi ke luar negeri. Para tersangka diyakini bertujuan untuk mengidentifikasi, memantau, menyerang, dan menculik warga asing di Turki. Pejabat Turki juga memperingatkan Israel akan 'konsekuensi serius' jika mereka memburu anggota militan Hamas di Turki."
  }
}